README.md
setup.cfg
setup.py
terraform_validate/__init__.py
terraform_validate/functional_test.py
terraform_validate/terraform_validate.py
terraform_validate/unit_test.py
terraform_validate.egg-info/PKG-INFO
terraform_validate.egg-info/SOURCES.txt
terraform_validate.egg-info/dependency_links.txt
terraform_validate.egg-info/requires.txt
terraform_validate.egg-info/top_level.txt