Metadata-Version: 1.1
Name: terraform-validate
Version: 2.6.0
Summary: A library that provides asserts for testing Terraform configuration
Home-page: https://github.com/elmundio87/terraform_validate
Author: Edmund Dipple
Author-email: elmundio1987@gmail.com
License: UNKNOWN
Download-URL: https://github.com/elmundio87/terraform_validate/tarball/2.6.0
Keywords: terraform,assert,testing
Platform: UNKNOWN
